.coveralls.yml
.gitignore
.travis.yml
LICENSE
MANIFEST.in
NOTICE
README.rst
requirements.txt
setup.py
docker/Dockerfile
docker/README.rst
docs/.nojekyll
docs/Makefile
docs/conf.py
docs/examples.rst
docs/fermilib.rst
docs/index.rst
docs/intro.rst
docs/make.bat
examples/fermilib_demo.ipynb
examples/performance_benchmarks.py
src/fermilib/__init__.py
src/fermilib/_version.py
src/fermilib/config.py
src/fermilib.egg-info/PKG-INFO
src/fermilib.egg-info/SOURCES.txt
src/fermilib.egg-info/dependency_links.txt
src/fermilib.egg-info/requires.txt
src/fermilib.egg-info/top_level.txt
src/fermilib/data/.gitignore
src/fermilib/data/H1-Li1_sto-3g_singlet_1.45.hdf5
src/fermilib/data/H2_sto-3g_singlet_0.1.hdf5
src/fermilib/data/H2_sto-3g_singlet_0.2.hdf5
src/fermilib/data/H2_sto-3g_singlet_0.3.hdf5
src/fermilib/data/H2_sto-3g_singlet_0.4.hdf5
src/fermilib/data/H2_sto-3g_singlet_0.5.hdf5
src/fermilib/data/H2_sto-3g_singlet_0.6.hdf5
src/fermilib/data/H2_sto-3g_singlet_0.7.hdf5
src/fermilib/data/H2_sto-3g_singlet_0.7414.hdf5
src/fermilib/data/H2_sto-3g_singlet_0.8.hdf5
src/fermilib/data/H2_sto-3g_singlet_0.9.hdf5
src/fermilib/data/H2_sto-3g_singlet_1.0.hdf5
src/fermilib/data/H2_sto-3g_singlet_1.1.hdf5
src/fermilib/data/H2_sto-3g_singlet_1.2.hdf5
src/fermilib/data/H2_sto-3g_singlet_1.3.hdf5
src/fermilib/data/H2_sto-3g_singlet_1.4.hdf5
src/fermilib/data/H2_sto-3g_singlet_1.5.hdf5
src/fermilib/data/H2_sto-3g_singlet_1.6.hdf5
src/fermilib/data/H2_sto-3g_singlet_1.7.hdf5
src/fermilib/data/H2_sto-3g_singlet_1.8.hdf5
src/fermilib/data/H2_sto-3g_singlet_1.9.hdf5
src/fermilib/data/H2_sto-3g_singlet_2.0.hdf5
src/fermilib/data/H2_sto-3g_singlet_2.1.hdf5
src/fermilib/data/H2_sto-3g_singlet_2.2.hdf5
src/fermilib/data/H2_sto-3g_singlet_2.3.hdf5
src/fermilib/data/H2_sto-3g_singlet_2.4.hdf5
src/fermilib/data/H2_sto-3g_singlet_2.5.hdf5
src/fermilib/data/H2_sto-3g_singlet_2.6.hdf5
src/fermilib/data/H2_sto-3g_singlet_2.7.hdf5
src/fermilib/data/H2_sto-3g_singlet_2.8.hdf5
src/fermilib/data/H2_sto-3g_singlet_2.9.hdf5
src/fermilib/data/H2_sto-3g_singlet_3.0.hdf5
src/fermilib/data/__init__.py
src/fermilib/data/geometry_example.txt
src/fermilib/ops/__init__.py
