Metadata-Version: 1.0
Name: fermilib
Version: 0.1a3
Summary: FermiLib - An open source package for analyzing, compiling and emulating quantum algorithms for simulation of fermions.
Home-page: http://www.projectq.ch
Author: FermiLib developers
Author-email: fermilib@projectq.ch
License: Apache 2
Platform: UNKNOWN
